[
    {
        "name": "BURGER KING, ванильный коктейль",
        "calories": "168 кКал",
        "priteins": "3,19 г",
        "fats": "8,74 г",
        "carbohydrates": "19,03 г"
    },
    {
        "name": "BURGER KING, гамбургер",
        "calories": "261 кКал",
        "priteins": "14,85 г",
        "fats": "10,55 г",
        "carbohydrates": "25,76 г"
    },
    {
        "name": "BURGER KING, двойной \"WHOPPER\", без сыра",
        "calories": "252 кКал",
        "priteins": "13,94 г",
        "fats": "15,66 г",
        "carbohydrates": "12,34 г"
    },
    {
        "name": "BURGER KING, двойной \"WHOPPER\", с сыром",
        "calories": "266 кКал",
        "priteins": "14,47 г",
        "fats": "17,06 г",
        "carbohydrates": "11,92 г"
    },
    {
        "name": "BURGER KING, драники",
        "calories": "302 кКал",
        "priteins": "2,8 г",
        "fats": "19,3 г",
        "carbohydrates": "27,07 г"
    },
    {
        "name": "BURGER KING, картошка фри",
        "calories": "280 кКал",
        "priteins": "3,23 г",
        "fats": "12,48 г",
        "carbohydrates": "35,8 г"
    },
    {
        "name": "BURGER KING, круассан \"CROISSAN'WICH\" с сосиской и сыром",
        "calories": "376 кКал",
        "priteins": "13,73 г",
        "fats": "25,45 г",
        "carbohydrates": "22,3 г"
    },
    {
        "name": "BURGER KING, круассан \"CROISSAN'WICH\" с сосиской, яйцом и сыром",
        "calories": "308 кКал",
        "priteins": "12,09 г",
        "fats": "21,78 г",
        "carbohydrates": "14,1 г"
    },
    {
        "name": "BURGER KING, круассан \"CROISSAN'WICH\" с яйцом и сыром",
        "calories": "283 кКал",
        "priteins": "10,35 г",
        "fats": "15,78 г",
        "carbohydrates": "24,09 г"
    },
    {
        "name": "BURGER KING, куриное филе \"CHICKEN TENDERS\"",
        "calories": "292 кКал",
        "priteins": "18,2 г",
        "fats": "15,25 г",
        "carbohydrates": "19,19 г"
    },
    {
        "name": "BURGER KING, куриный сэндвич \"Original Chicken Sandwich\"",
        "calories": "286 кКал",
        "priteins": "12,14 г",
        "fats": "14,69 г",
        "carbohydrates": "23,82 г"
    },
    {
        "name": "BURGER KING, сэндвич \"WHOPPER\", без сыра",
        "calories": "233 кКал",
        "priteins": "10,74 г",
        "fats": "12,84 г",
        "carbohydrates": "16,75 г"
    },
    {
        "name": "BURGER KING, сэндвич \"WHOPPER\", с сыром",
        "calories": "250 кКал",
        "priteins": "11,19 г",
        "fats": "15,33 г",
        "carbohydrates": "15,7 г"
    },
    {
        "name": "BURGER KING, французские гренки",
        "calories": "349 кКал",
        "priteins": "6 г",
        "fats": "17,74 г",
        "carbohydrates": "39,81 г"
    },
    {
        "name": "BURGER KING, чизбургер",
        "calories": "286 кКал",
        "priteins": "14,57 г",
        "fats": "14,81 г",
        "carbohydrates": "22,71 г"
    },
    {
        "name": "DOMINO'S, пицца \"EXTRAVAGANZZA FEAST\", на классическом корже, сформированном вручную, 14 дюймов",
        "calories": "244 кКал",
        "priteins": "10,33 г",
        "fats": "11,1 г",
        "carbohydrates": "23,72 г"
    },
    {
        "name": "DOMINO'S, пицца с паперони \"Pepperoni Pizza\", на замороженном корже, 14 дюймов",
        "calories": "283 кКал",
        "priteins": "11,52 г",
        "fats": "12,1 г",
        "carbohydrates": "29,49 г"
    },
    {
        "name": "DOMINO'S, пицца с паперони \"Pepperoni Pizza\", на классическом корже, сформированном вручную, 14 дюймов",
        "calories": "273 кКал",
        "priteins": "11,25 г",
        "fats": "11,18 г",
        "carbohydrates": "29,76 г"
    },
    {
        "name": "DOMINO'S, сырная пицца \"Cheese Pizza\", на замороженном корже, 14 дюймов",
        "calories": "265 кКал",
        "priteins": "10,76 г",
        "fats": "9,83 г",
        "carbohydrates": "31,08 г"
    },
    {
        "name": "DOMINO'S, сырная пицца \"Cheese Pizza\", на классическом корже, сформированном вручную, 14 дюймов",
        "calories": "257 кКал",
        "priteins": "10,8 г",
        "fats": "8,97 г",
        "carbohydrates": "31,04 г"
    },
    {
        "name": "DOMINO'S, сырная пицца \"Cheese Pizza\", на тонком корже с кусочками арахиса",
        "calories": "298 кКал",
        "priteins": "12,33 г",
        "fats": "15,1 г",
        "carbohydrates": "25,68 г"
    },
    {
        "name": "KENTUCKY FRIED CHICKEN, бисквит, информация состоянием на январь 2007",
        "calories": "358 кКал",
        "priteins": "7,5 г",
        "fats": "17,05 г",
        "carbohydrates": "41,55 г"
    },
    {
        "name": "KENTUCKY FRIED CHICKEN, жареная в панировке курица \"EXTRA CRISPY\", бедра, мясо и шкурка, информация состоянием на январь 2007",
        "calories": "309 кКал",
        "priteins": "17,17 г",
        "fats": "22,14 г",
        "carbohydrates": "10,3 г"
    },
    {
        "name": "KENTUCKY FRIED CHICKEN, жареная в панировке курица \"EXTRA CRISPY\", крылышки, мясо и шкурка, информация состоянием на  январе 2007",
        "calories": "337 кКал",
        "priteins": "20,8 г",
        "fats": "23 г",
        "carbohydrates": "11,66 г"
    },
    {
        "name": "KENTUCKY FRIED CHICKEN, жареная в панировке курица \"EXTRA CRISPY\", ножки, мясо и шкурка, информация состоянием на январь 2007",
        "calories": "274 кКал",
        "priteins": "20,62 г",
        "fats": "17,73 г",
        "carbohydrates": "7,96 г"
    },
    {
        "name": "KENTUCKY FRIED CHICKEN, жареная в панировке курица \"EXTRA CRISPY\", шкурка, информация состоянием на январь 2007",
        "calories": "464 кКал",
        "priteins": "10,96 г",
        "fats": "36,61 г",
        "carbohydrates": "21,04 г"
    },
    {
        "name": "KENTUCKY FRIED CHICKEN, жареная в панировке курица \"ORIGINAL RECIPE\", бедра, мясо и шкурка, информация состоянием на январь 2007",
        "calories": "269 кКал",
        "priteins": "18,9 г",
        "fats": "17,73 г",
        "carbohydrates": "8,46 г"
    },
    {
        "name": "KENTUCKY FRIED CHICKEN, жареная в панировке курица \"ORIGINAL RECIPE\", грудка, мясо и шкурка, информация состоянием на январь 2007",
        "calories": "231 кКал",
        "priteins": "21,94 г",
        "fats": "13,11 г",
        "carbohydrates": "6,28 г"
    },
    {
        "name": "KENTUCKY FRIED CHICKEN, жареная в панировке курица \"ORIGINAL RECIPE\", крылышки, мясо и шкурка, информация состоянием на  январь 2007",
        "calories": "297 кКал",
        "priteins": "21,7 г",
        "fats": "18,9 г",
        "carbohydrates": "9,93 г"
    },
    {
        "name": "KENTUCKY FRIED CHICKEN, жареная в панировке курица \"ORIGINAL RECIPE\", ножки, мясо и шкурка, информация состоянием на  январь 2007",
        "calories": "239 кКал",
        "priteins": "22,3 г",
        "fats": "14,22 г",
        "carbohydrates": "5,39 г"
    },
    {
        "name": "KENTUCKY FRIED CHICKEN, жареная в панировке курица \"ORIGINAL RECIPE\", шкурка, информация состоянием на  январь 2007",
        "calories": "384 кКал",
        "priteins": "14,17 г",
        "fats": "28,01 г",
        "carbohydrates": "18,79 г"
    },
    {
        "name": "KENTUCKY FRIED CHICKEN, жареная курица \"EXTRA CRISPY\", бедра, только мясо,  информация состоянием на  январь 2007",
        "calories": "179 кКал",
        "priteins": "22,41 г",
        "fats": "9,96 г",
        "carbohydrates": "0 г"
    },
    {
        "name": "KENTUCKY FRIED CHICKEN, жареная курица \"EXTRA CRISPY\", грудка, только мясо, информация состоянием на январь 2007",
        "calories": "153 кКал",
        "priteins": "27,25 г",
        "fats": "4,82 г",
        "carbohydrates": "0,25 г"
    },
    {
        "name": "KENTUCKY FRIED CHICKEN, жареная курица \"EXTRA CRISPY\", крылышки, только мясо, информация состоянием на  январь 2007",
        "calories": "236 кКал",
        "priteins": "28,67 г",
        "fats": "12,13 г",
        "carbohydrates": "2,97 г"
    },
    {
        "name": "KENTUCKY FRIED CHICKEN, жареная курица \"EXTRA CRISPY\", ножки, только мясо, информация состоянием на  январь 2007",
        "calories": "170 кКал",
        "priteins": "25,9 г",
        "fats": "7,43 г",
        "carbohydrates": "0 г"
    },
    {
        "name": "KENTUCKY FRIED CHICKEN, жареная курица \"ORIGINAL RECIPE\" ножки, только мясо, информация состоянием на  январь 2007",
        "calories": "175 кКал",
        "priteins": "26,3 г",
        "fats": "7,66 г",
        "carbohydrates": "0,11 г"
    },
    {
        "name": "KENTUCKY FRIED CHICKEN, жареная курица \"ORIGINAL RECIPE\", бедра, только мясо, информация состоянием на  январь 2007",
        "calories": "175 кКал",
        "priteins": "22,78 г",
        "fats": "9,31 г",
        "carbohydrates": "0,01 г"
    },
    {
        "name": "KENTUCKY FRIED CHICKEN, жареная курица \"ORIGINAL RECIPE\", грудка, только мясо, информация состоянием на  январь 2007",
        "calories": "149 кКал",
        "priteins": "26,89 г",
        "fats": "4,56 г",
        "carbohydrates": "0 г"
    },
    {
        "name": "KENTUCKY FRIED CHICKEN, жареная курица \"ORIGINAL RECIPE\", крылышки, только мясо, информация состоянием на  январь 2007",
        "calories": "216 кКал",
        "priteins": "28,65 г",
        "fats": "10,49 г",
        "carbohydrates": "1,76 г"
    },
    {
        "name": "KENTUCKY FRIED CHICKEN, жаренаяв панировке курица \"EXTRA CRISPY\", грудка, мясо и шкурка, информация состоянием на янваье 2007",
        "calories": "268 кКал",
        "priteins": "21,24 г",
        "fats": "16,55 г",
        "carbohydrates": "8,47 г"
    },
    {
        "name": "KENTUCKY FRIED CHICKEN, куринный попкорн, информация состоянием на январь 2007",
        "calories": "351 кКал",
        "priteins": "17,67 г",
        "fats": "21,74 г",
        "carbohydrates": "20,18 г"
    },
    {
        "name": "KENTUCKY FRIED CHICKEN, салат из капусты",
        "calories": "144 кКал",
        "priteins": "0,91 г",
        "fats": "8,64 г",
        "carbohydrates": "13,65 г"
    },
    {
        "name": "KENTUCKY FRIED CHICKEN, хрустящие куринные полосочки, информация состоянием на  январь 2007",
        "calories": "274 кКал",
        "priteins": "20,25 г",
        "fats": "15,42 г",
        "carbohydrates": "12,26 г"
    },
    {
        "name": "LITTLE CAESARS, пицца с мясом и овощами, на оригинальном корже, 14 дюймов",
        "calories": "243 кКал",
        "priteins": "12,12 г",
        "fats": "11,35 г",
        "carbohydrates": "21 г"
    },
    {
        "name": "LITTLE CAESARS, пицца с паперони \"Original Round Pepperoni Pizza\", на стандартном корже, 14 дюймов",
        "calories": "273 кКал",
        "priteins": "13,59 г",
        "fats": "10,5 г",
        "carbohydrates": "29,31 г"
    },
    {
        "name": "LITTLE CAESARS, пицца с паперони \"Pepperoni Pizza\", на большом замороженном корже, 14 дюймов",
        "calories": "265 кКал",
        "priteins": "12,93 г",
        "fats": "10,81 г",
        "carbohydrates": "27,53 г"
    },
    {
        "name": "LITTLE CAESARS, сырная пицца \"Cheese Pizza\", на большом замороженном корже, 14 дюймов",
        "calories": "263 кКал",
        "priteins": "12,63 г",
        "fats": "10,22 г",
        "carbohydrates": "28,8 г"
    },
    {
        "name": "LITTLE CAESARS, сырная пицца \"Cheese Pizza\", на тонком корже, 14 дюймов",
        "calories": "309 кКал",
        "priteins": "16,23 г",
        "fats": "16,99 г",
        "carbohydrates": "21,25 г"
    },
    {
        "name": "LITTLE CAESARS, сырная пицца \"Original Round Cheese Pizza\", на стандартном корже, 14 дюймов",
        "calories": "265 кКал",
        "priteins": "13,39 г",
        "fats": "9,54 г",
        "carbohydrates": "29,8 г"
    },
    {
        "name": "McDONALD'S, \"BIG MAC\"",
        "calories": "257 кКал",
        "priteins": "11,82 г",
        "fats": "14,96 г",
        "carbohydrates": "18,48 г"
    },
    {
        "name": "McDONALD'S, \"BIG MAC\" (без соуса Big Mac)",
        "calories": "234 кКал",
        "priteins": "12,79 г",
        "fats": "11,57 г",
        "carbohydrates": "19,31 г"
    },
    {
        "name": "McDONALD'S, \"Chicken McNUGGETS\"",
        "calories": "302 кКал",
        "priteins": "15,79 г",
        "fats": "19,81 г",
        "carbohydrates": "15,09 г"
    },
    {
        "name": "McDONALD'S, бисквит с беконом, яйцом и сыром",
        "calories": "304 кКал",
        "priteins": "13,45 г",
        "fats": "18,77 г",
        "carbohydrates": "21,36 г"
    },
    {
        "name": "McDONALD'S, бисквит с котлетой",
        "calories": "376 кКал",
        "priteins": "9,62 г",
        "fats": "25,4 г",
        "carbohydrates": "26 г"
    },
    {
        "name": "McDONALD'S, бисквит с котлетой и яйцом",
        "calories": "311 кКал",
        "priteins": "11,27 г",
        "fats": "22,26 г",
        "carbohydrates": "18,48 г"
    },
    {
        "name": "McDONALD'S, буррито с котлетой",
        "calories": "262 кКал",
        "priteins": "11,54 г",
        "fats": "15,15 г",
        "carbohydrates": "21,39 г"
    },
    {
        "name": "McDONALD'S, гамбургер",
        "calories": "264 кКал",
        "priteins": "12,92 г",
        "fats": "10,09 г",
        "carbohydrates": "28,98 г"
    },
    {
        "name": "McDONALD'S, готовые завтраки \"BIG BREAKFAST\"",
        "calories": "285 кКал",
        "priteins": "10,16 г",
        "fats": "19,37 г",
        "carbohydrates": "16,4 г"
    },
    {
        "name": "McDONALD'S, двойной сэндвич \"QUARTER POUNDER\" с сыром",
        "calories": "262 кКал",
        "priteins": "16,96 г",
        "fats": "16,22 г",
        "carbohydrates": "13,43 г"
    },
    {
        "name": "McDONALD'S, двойной чизбургер",
        "calories": "282 кКал",
        "priteins": "15,5 г",
        "fats": "16,09 г",
        "carbohydrates": "17,99 г"
    },
    {
        "name": "McDONALD'S, драники",
        "calories": "262 кКал",
        "priteins": "2,26 г",
        "fats": "16,46 г",
        "carbohydrates": "26,3 г"
    },
    {
        "name": "McDONALD'S, завтрак \"Deluxe\", с сиропом и маргарином",
        "calories": "285 кКал",
        "priteins": "7,56 г",
        "fats": "15,23 г",
        "carbohydrates": "28,48 г"
    },
    {
        "name": "McDONALD'S, йогуртово-фруктовое Парфе",
        "calories": "105 кКал",
        "priteins": "2,73 г",
        "fats": "1,3 г",
        "carbohydrates": "19,72 г"
    },
    {
        "name": "McDONALD'S, йогуртово-фруктовое Парфе (без гранолы)",
        "calories": "90 кКал",
        "priteins": "2,47 г",
        "fats": "1,13 г",
        "carbohydrates": "16,77 г"
    },
    {
        "name": "McDONALD'S, картошка фри",
        "calories": "323 кКал",
        "priteins": "3,41 г",
        "fats": "15,47 г",
        "carbohydrates": "38,68 г"
    },
    {
        "name": "McDONALD'S, котлета McGRIDDLES",
        "calories": "312 кКал",
        "priteins": "8,41 г",
        "fats": "17,76 г",
        "carbohydrates": "30,25 г"
    },
    {
        "name": "McDONALD'S, котлета McMuffin",
        "calories": "333 кКал",
        "priteins": "12,66 г",
        "fats": "21,06 г",
        "carbohydrates": "23,12 г"
    },
    {
        "name": "McDONALD'S, котлета McMuffin с яйцом",
        "calories": "274 кКал",
        "priteins": "12,59 г",
        "fats": "17,83 г",
        "carbohydrates": "16,38 г"
    },
    {
        "name": "McDONALD'S, котлета McMuffin с яйцом и сыром",
        "calories": "283 кКал",
        "priteins": "10,77 г",
        "fats": "17,73 г",
        "carbohydrates": "21,44 г"
    },
    {
        "name": "McDONALD'S, мороженное \"McFLURRY\" с конфетами \"M and M'S\"",
        "calories": "177 кКал",
        "priteins": "4,02 г",
        "fats": "6,46 г",
        "carbohydrates": "26,62 г"
    },
    {
        "name": "McDONALD'S, мороженное \"McFLURRY\" с печеньем \"OREO\"",
        "calories": "165 кКал",
        "priteins": "3,97 г",
        "fats": "5,66 г",
        "carbohydrates": "25,45 г"
    },
    {
        "name": "McDONALD'S, обезжиренное ванильное мороженое, рожок",
        "calories": "162 кКал",
        "priteins": "4,24 г",
        "fats": "4,86 г",
        "carbohydrates": "26,26 г"
    },
    {
        "name": "McDONALD'S, оладьи",
        "calories": "228 кКал",
        "priteins": "6 г",
        "fats": "5,84 г",
        "carbohydrates": "36,87 г"
    },
    {
        "name": "McDONALD'S, оладьи (с двумя шариками масла и сиропом)",
        "calories": "272 кКал",
        "priteins": "4,05 г",
        "fats": "8,06 г",
        "carbohydrates": "45,18 г"
    },
    {
        "name": "McDONALD'S, оладьи с сосисками",
        "calories": "294 кКал",
        "priteins": "7,81 г",
        "fats": "12,5 г",
        "carbohydrates": "35,95 г"
    },
    {
        "name": "McDONALD'S, пломбир клубничный",
        "calories": "158 кКал",
        "priteins": "3,19 г",
        "fats": "3,95 г",
        "carbohydrates": "28,09 г"
    },
    {
        "name": "McDONALD'S, пломбир с горячей карамелью",
        "calories": "188 кКал",
        "priteins": "3,58 г",
        "fats": "4,89 г",
        "carbohydrates": "33,36 г"
    },
    {
        "name": "McDONALD'S, пломбир с горячей помадкой",
        "calories": "186 кКал",
        "priteins": "4,14 г",
        "fats": "5,91 г",
        "carbohydrates": "29,65 г"
    },
    {
        "name": "McDONALD'S, рыбный сэндвич \"FILET-O-FISH\"",
        "calories": "282 кКал",
        "priteins": "11,26 г",
        "fats": "14,64 г",
        "carbohydrates": "24,99 г"
    },
    {
        "name": "McDONALD'S, рыбный сэндвич \"FILET-O-FISH\" (без соуса тартар)",
        "calories": "243 кКал",
        "priteins": "12,47 г",
        "fats": "7,62 г",
        "carbohydrates": "30,08 г"
    },
    {
        "name": "McDONALD'S, салат с беконом и хрустящей курятиной \"Bacon Ranch Salad\"",
        "calories": "122 кКал",
        "priteins": "8,82 г",
        "fats": "6,3 г",
        "carbohydrates": "5,08 г"
    },
    {
        "name": "McDONALD'S, сэндвич \"McCHICKEN\" (без майонеза)",
        "calories": "240 кКал",
        "priteins": "11,08 г",
        "fats": "8,46 г",
        "carbohydrates": "29,55 г"
    },
    {
        "name": "McDONALD'S, сэндвич \"McMUFFIN\" с яйцом",
        "calories": "228 кКал",
        "priteins": "13,64 г",
        "fats": "9,66 г",
        "carbohydrates": "20,57 г"
    },
    {
        "name": "McDONALD'S, сэндвич \"QUARTER POUNDER\"",
        "calories": "244 кКал",
        "priteins": "14,1 г",
        "fats": "11,55 г",
        "carbohydrates": "20,57 г"
    },
    {
        "name": "McDONALD'S, сэндвич \"QUARTER POUNDER\" (с сыром)",
        "calories": "258 кКал",
        "priteins": "14,59 г",
        "fats": "14,22 г",
        "carbohydrates": "18,55 г"
    },
    {
        "name": "McDONALD'S, сэндвич с беконом, яйцом и сыром \"McGRIDDLES\"",
        "calories": "272 кКал",
        "priteins": "12,03 г",
        "fats": "13,19 г",
        "carbohydrates": "25,39 г"
    },
    {
        "name": "McDONALD'S, чизбургер",
        "calories": "263 кКал",
        "priteins": "12,97 г",
        "fats": "11,79 г",
        "carbohydrates": "26,71 г"
    },
    {
        "name": "PAPA JOHN'S, пицца \"Works Pizza\", на фирменном корже, 14 дюймов",
        "calories": "240 кКал",
        "priteins": "10,27 г",
        "fats": "10,21 г",
        "carbohydrates": "24,19 г"
    },
    {
        "name": "PAPA JOHN'S, пицца с паперони \"Pepperoni Pizza\", на оригинальном корже, 14 дюймов",
        "calories": "275 кКал",
        "priteins": "11,97 г",
        "fats": "11,86 г",
        "carbohydrates": "28,84 г"
    },
    {
        "name": "PAPA JOHN'S, сырная пицца \"Cheese Pizza\", на оригинальмом корже, 14 дюймов",
        "calories": "260 кКал",
        "priteins": "11,53 г",
        "fats": "9,25 г",
        "carbohydrates": "30,84 г"
    },
    {
        "name": "PAPA JOHN'S, сырная пицца \"Cheese Pizza\", на тонком корже, 14 дюймов",
        "calories": "295 кКал",
        "priteins": "12,29 г",
        "fats": "15,66 г",
        "carbohydrates": "23,96 г"
    },
    {
        "name": "PIZZA HUT, пицца \"Super Supreme Pizza\", на стандартном корже, 12 дюймов",
        "calories": "243 кКал",
        "priteins": "10,9 г",
        "fats": "10,72 г",
        "carbohydrates": "23,62 г"
    },
    {
        "name": "PIZZA HUT, пицца \"Super Supreme Pizza\", на стандартном корже, 14 дюймов",
        "calories": "248 кКал",
        "priteins": "11,34 г",
        "fats": "10,95 г",
        "carbohydrates": "23,71 г"
    },
    {
        "name": "PIZZA HUT, пицца с паперони \"Pepperoni Pizza\", на стандартном корже, 12 дюймов",
        "calories": "280 кКал",
        "priteins": "12,86 г",
        "fats": "11,38 г",
        "carbohydrates": "29,85 г"
    },
    {
        "name": "PIZZA HUT, пицца с паперони \"Pepperoni Pizza\", на стандартном корже, 14 дюймов",
        "calories": "291 кКал",
        "priteins": "12,23 г",
        "fats": "12,63 г",
        "carbohydrates": "29,51 г"
    },
    {
        "name": "PIZZA HUT, пицца с паперони \"Pepperoni Pizza\", на толстом корже, 12 дюймов",
        "calories": "298 кКал",
        "priteins": "11,97 г",
        "fats": "14,21 г",
        "carbohydrates": "28,69 г"
    },
    {
        "name": "PIZZA HUT, пицца с паперони \"Pepperoni Pizza\", на толстом корже, 14 дюймов",
        "calories": "291 кКал",
        "priteins": "11,47 г",
        "fats": "13,07 г",
        "carbohydrates": "29,79 г"
    },
    {
        "name": "PIZZA HUT, сырная пицца \"Cheese Pizza\", на стандартном корже, 12 дюймов",
        "calories": "271 кКал",
        "priteins": "11,93 г",
        "fats": "10,89 г",
        "carbohydrates": "29,42 г"
    },
    {
        "name": "PIZZA HUT, сырная пицца \"Cheese Pizza\", на стандартном корже, 14 дюймов",
        "calories": "275 кКал",
        "priteins": "11,98 г",
        "fats": "10,42 г",
        "carbohydrates": "31,02 г"
    },
    {
        "name": "PIZZA HUT, сырная пицца \"Cheese Pizza\", на толстом корже, 12 дюймов",
        "calories": "280 кКал",
        "priteins": "11,73 г",
        "fats": "12,56 г",
        "carbohydrates": "28,23 г"
    },
    {
        "name": "PIZZA HUT, сырная пицца \"Cheese Pizza\", на толстом корже, 14 дюймов",
        "calories": "276 кКал",
        "priteins": "10,85 г",
        "fats": "11,25 г",
        "carbohydrates": "30,75 г"
    },
    {
        "name": "PIZZA HUT, сырная пицца \"Cheese Pizza\", на тонком хрустящем корже, 12 дюймов",
        "calories": "303 кКал",
        "priteins": "15,29 г",
        "fats": "14,1 г",
        "carbohydrates": "27,04 г"
    },
    {
        "name": "PIZZA HUT, сырная пицца \"Cheese Pizza\", на тонком хрустящем корже, 14 дюймов",
        "calories": "306 кКал",
        "priteins": "13,37 г",
        "fats": "12,8 г",
        "carbohydrates": "31,82 г"
    },
    {
        "name": "POPEYES, бисквит, информация состоянием на ноябрь 2007",
        "calories": "401 кКал",
        "priteins": "6 г",
        "fats": "23,71 г",
        "carbohydrates": "37,15 г"
    },
    {
        "name": "POPEYES, жареная в панировке курица, бедра, мясо и шкурка, информация состоянием на январь 2007",
        "calories": "310 кКал",
        "priteins": "19,14 г",
        "fats": "20,99 г",
        "carbohydrates": "10,7 г"
    },
    {
        "name": "POPEYES, жареная в панировке курица, грудка, мясо и шкурка, информация состоянием на январь 2007",
        "calories": "274 кКал",
        "priteins": "21,67 г",
        "fats": "16,47 г",
        "carbohydrates": "9,43 г"
    },
    {
        "name": "POPEYES, жареная в панировке курица, крылышки, мясо и шкурка, информация состоянием на  январь 2007",
        "calories": "338 кКал",
        "priteins": "20,4 г",
        "fats": "22,48 г",
        "carbohydrates": "12,92 г"
    },
    {
        "name": "POPEYES, жареная в панировке курица, ножки, мясо и шкурка, острые, информация состоянием на  январь 2007",
        "calories": "293 кКал",
        "priteins": "20,44 г",
        "fats": "19,14 г",
        "carbohydrates": "9,84 г"
    },
    {
        "name": "POPEYES, жареная в панировке курица, шкурка, информация состоянием на  январь 2007",
        "calories": "433 кКал",
        "priteins": "13,96 г",
        "fats": "32,32 г",
        "carbohydrates": "20,54 г"
    },
    {
        "name": "POPEYES, жареная курица, бедра, только мясо, информация состоянием на  январь 2007",
        "calories": "188 кКал",
        "priteins": "24,31 г",
        "fats": "9,66 г",
        "carbohydrates": "0,85 г"
    },
    {
        "name": "POPEYES, жареная курица, грудка, только мясо, информация состоянием на  январь 2007",
        "calories": "157 кКал",
        "priteins": "28,98 г",
        "fats": "4,52 г",
        "carbohydrates": "0 г"
    },
    {
        "name": "POPEYES, жареная курица, крылышки, только мясо, информация состоянием на  январь 2007",
        "calories": "212 кКал",
        "priteins": "28,94 г",
        "fats": "9,42 г",
        "carbohydrates": "2,9 г"
    },
    {
        "name": "POPEYES, жареная курица, ножки, только мясо, информация состоянием на  январь 2007",
        "calories": "170 кКал",
        "priteins": "26,51 г",
        "fats": "7,14 г",
        "carbohydrates": "0,04 г"
    },
    {
        "name": "POPEYES, куринные полосочки, информация состоянием на  2006 год",
        "calories": "271 кКал",
        "priteins": "19,2 г",
        "fats": "13,01 г",
        "carbohydrates": "18,51 г"
    },
    {
        "name": "POPEYES, острые куринные полосочки, информация состоянием на  2006 год",
        "calories": "253 кКал",
        "priteins": "19,61 г",
        "fats": "11,2 г",
        "carbohydrates": "17,32 г"
    },
    {
        "name": "POPEYES, салат из капусты",
        "calories": "161 кКал",
        "priteins": "0,98 г",
        "fats": "11,18 г",
        "carbohydrates": "12,42 г"
    },
    {
        "name": "TACO BELL, буррито \"SUPREME\" с говядиной",
        "calories": "183 кКал",
        "priteins": "7,03 г",
        "fats": "6,8 г",
        "carbohydrates": "19,67 г"
    },
    {
        "name": "TACO BELL, буррито \"SUPREME\" с курицей",
        "calories": "179 кКал",
        "priteins": "9,84 г",
        "fats": "6,42 г",
        "carbohydrates": "18,11 г"
    },
    {
        "name": "TACO BELL, буррито \"SUPREME\" со стейком",
        "calories": "183 кКал",
        "priteins": "9,13 г",
        "fats": "7,27 г",
        "carbohydrates": "17,92 г"
    },
    {
        "name": "TACO BELL, буррито с бобами",
        "calories": "209 кКал",
        "priteins": "7,35 г",
        "fats": "6,05 г",
        "carbohydrates": "27,03 г"
    },
    {
        "name": "TACO BELL, мягкое тако (тако с пшеничной лепешкой) с говядиной",
        "calories": "206 кКал",
        "priteins": "9,25 г",
        "fats": "9,75 г",
        "carbohydrates": "17,33 г"
    },
    {
        "name": "TACO BELL, мягкое тако (тако с пшеничной лепешкой) с курицей",
        "calories": "189 кКал",
        "priteins": "13,3 г",
        "fats": "6,35 г",
        "carbohydrates": "18,49 г"
    },
    {
        "name": "TACO BELL, мягкое тако (тако с пшеничной лепешкой) со стейком",
        "calories": "225 кКал",
        "priteins": "11,81 г",
        "fats": "12,1 г",
        "carbohydrates": "15,62 г"
    },
    {
        "name": "TACO BELL, начо (картофельные чипсы)",
        "calories": "350 кКал",
        "priteins": "4,32 г",
        "fats": "21,5 г",
        "carbohydrates": "31,71 г"
    },
    {
        "name": "TACO BELL, начо (картофельные чипсы) с соусом сюприм",
        "calories": "246 кКал",
        "priteins": "7,59 г",
        "fats": "13,65 г",
        "carbohydrates": "23,09 г"
    },
    {
        "name": "TACO BELL, Оригинальное тако с говядиной",
        "calories": "229 кКал",
        "priteins": "8,86 г",
        "fats": "12,7 г",
        "carbohydrates": "15,95 г"
    },
    {
        "name": "TACO BELL, салат тако",
        "calories": "170 кКал",
        "priteins": "6,69 г",
        "fats": "9,17 г",
        "carbohydrates": "12,1 г"
    },
    {
        "name": "WENDY'S, гамбургер \"CLASSIC SINGLE\", без сыра",
        "calories": "213 кКал",
        "priteins": "12,63 г",
        "fats": "10,6 г",
        "carbohydrates": "15,52 г"
    },
    {
        "name": "WENDY'S, гамбургер \"CLASSIC SINGLE\", с сыром",
        "calories": "221 кКал",
        "priteins": "14,87 г",
        "fats": "11,6 г",
        "carbohydrates": "12,8 г"
    },
    {
        "name": "WENDY'S, гамбургер \"Jr. Hamburger\", без сыра",
        "calories": "243 кКал",
        "priteins": "12,62 г",
        "fats": "8,75 г",
        "carbohydrates": "26,75 г"
    },
    {
        "name": "WENDY'S, гамбургер \"Jr. Hamburger\", с сыром",
        "calories": "256 кКал",
        "priteins": "13,06 г",
        "fats": "11,5 г",
        "carbohydrates": "23,57 г"
    },
    {
        "name": "WENDY'S, замороженные десерты на каждый день \"Frosty Dairy Dessert\"",
        "calories": "132 кКал",
        "priteins": "3,49 г",
        "fats": "2,6 г",
        "carbohydrates": "20,32 г"
    },
    {
        "name": "WENDY'S, классический двойной сэндвич \"CLASSIC DOUBLE\", с сыром",
        "calories": "241 кКал",
        "priteins": "16,52 г",
        "fats": "14,2 г",
        "carbohydrates": "10,61 г"
    },
    {
        "name": "WENDY'S, куринные нагетсы",
        "calories": "326 кКал",
        "priteins": "16,46 г",
        "fats": "22,55 г",
        "carbohydrates": "14,31 г"
    },
    {
        "name": "WENDY'S, сэндвич с куриным филе по-домашнему (Homestyle Chicken Fillet Sandwich)",
        "calories": "214 кКал",
        "priteins": "13,78 г",
        "fats": "8,1 г",
        "carbohydrates": "20,25 г"
    },
    {
        "name": "WENDY'S, сэндвич с куриным филе, приготовленным на гриле (Ultimate Chicken Grill Sandwich)",
        "calories": "179 кКал",
        "priteins": "14,73 г",
        "fats": "5 г",
        "carbohydrates": "17,78 г"
    },
    {
        "name": "Легкое мягкое мороженое, смешанное с конфетами из молочного шоколада",
        "calories": "182 кКал",
        "priteins": "4,02 г",
        "fats": "6,46 г",
        "carbohydrates": "26,62 г"
    },
    {
        "name": "Легкое мягкое мороженое, смешанное с кусочками печенья",
        "calories": "169 кКал",
        "priteins": "3,97 г",
        "fats": "5,66 г",
        "carbohydrates": "25,45 г"
    },
    {
        "name": "Макдональдс, Бэкон Ранч, салат без цыпленка",
        "calories": "61 кКал",
        "priteins": "4,14 г",
        "fats": "3,64 г",
        "carbohydrates": "2,7 г"
    },
    {
        "name": "Макдональдс, Бэкон Ранч, салат с цыпленком гриль",
        "calories": "81 кКал",
        "priteins": "10,28 г",
        "fats": "3,14 г",
        "carbohydrates": "2,64 г"
    },
    {
        "name": "Макдональдс, Сайд Салат",
        "calories": "20 кКал",
        "priteins": "1,03 г",
        "fats": "0,19 г",
        "carbohydrates": "2,7 г"
    },
    {
        "name": "Пицца, с мясом и овощами, на растущем корже, замороженная, приготовленная",
        "calories": "271 кКал",
        "priteins": "12,63 г",
        "fats": "11,75 г",
        "carbohydrates": "26,48 г"
    },
    {
        "name": "Пицца, с мясом и овощами, на стандартном корже, замороженная, приготовленная",
        "calories": "276 кКал",
        "priteins": "11,28 г",
        "fats": "14,43 г",
        "carbohydrates": "22,94 г"
    },
    {
        "name": "Пицца, с паперони, на стандартном корже, замороженная, приготовленная",
        "calories": "274 кКал",
        "priteins": "14,38 г",
        "fats": "13,13 г",
        "carbohydrates": "22,69 г"
    },
    {
        "name": "Пицца, с сыром, замороженная, приготовленная",
        "calories": "268 кКал",
        "priteins": "10,36 г",
        "fats": "12,28 г",
        "carbohydrates": "26,82 г"
    },
    {
        "name": "Пицца, с сыром, на растущем корже, замороженная, приготовленная",
        "calories": "260 кКал",
        "priteins": "12,37 г",
        "fats": "8,78 г",
        "carbohydrates": "30,41 г"
    },
    {
        "name": "Сэндвич с сосиской \"Sausage Griddle Cake Sandwich\"",
        "calories": "318 кКал",
        "priteins": "8,41 г",
        "fats": "17,76 г",
        "carbohydrates": "30,25 г"
    },
    {
        "name": "Сэндвич с яйцом, сыром и беконом \"Griddle Cak\"",
        "calories": "272 кКал",
        "priteins": "12,03 г",
        "fats": "13,19 г",
        "carbohydrates": "25,39 г"
    },
    {
        "name": "Сэндвич с яйцом, сыром и сосиской \"Griddle Cak\"",
        "calories": "291 кКал",
        "priteins": "10,77 г",
        "fats": "17,73 г",
        "carbohydrates": "21,44 г"
    },
    {
        "name": "Фаст фуд, жареный цыпленок, бедрышки, мясо с кожицей, в панировке",
        "calories": "274 кКал",
        "priteins": "19,23 г",
        "fats": "18,07 г",
        "carbohydrates": "8,58 г"
    },
    {
        "name": "Фаст фуд, жареный цыпленок, бедрышки, только мясо, без кожицы и без панировки",
        "calories": "178 кКал",
        "priteins": "23,21 г",
        "fats": "9,41 г",
        "carbohydrates": "0,24 г"
    },
    {
        "name": "Фаст фуд, жареный цыпленок, голень, мясо с кожицей, в панировке",
        "calories": "267 кКал",
        "priteins": "21,13 г",
        "fats": "16,92 г",
        "carbohydrates": "7,09 г"
    },
    {
        "name": "Фаст фуд, жареный цыпленок, голень, только мясо, без кожицы и без панировки",
        "calories": "172 кКал",
        "priteins": "26,24 г",
        "fats": "7,41 г",
        "carbohydrates": "0 г"
    },
    {
        "name": "Фаст фуд, жареный цыпленок, грудки, только мясо, без кожицы и без панировки",
        "calories": "153 кКал",
        "priteins": "27,93 г",
        "fats": "4,54 г",
        "carbohydrates": "0 г"
    },
    {
        "name": "Фаст фуд, жареный цыпленок, кожа в панировке",
        "calories": "398 кКал",
        "priteins": "14,11 г",
        "fats": "29,22 г",
        "carbohydrates": "19,26 г"
    },
    {
        "name": "Фаст фуд, жареный цыпленок, крылышки, мясо с кожицей, в панировке",
        "calories": "310 кКал",
        "priteins": "21,14 г",
        "fats": "20,09 г",
        "carbohydrates": "11,09 г"
    },
    {
        "name": "Фаст фуд, жареный цыпленок, крылышки, только мясо, без кожицы и без панировки",
        "calories": "215 кКал",
        "priteins": "28,77 г",
        "fats": "10,2 г",
        "carbohydrates": "2,13 г"
    },
    {
        "name": "Фаст фуд, клаб сэндвич (трехслойный), с курицей-гриль, беконом, томатами, сыром, салатом и майонезом",
        "calories": "220 кКал",
        "priteins": "17,19 г",
        "fats": "8,05 г",
        "carbohydrates": "18,67 г"
    },
    {
        "name": "Фаст фуд, клаб сэндвич (трехслойный), с хрустящей курицей, беконом, томатами, сыром, салатом и майонезом",
        "calories": "257 кКал",
        "priteins": "15,38 г",
        "fats": "11,76 г",
        "carbohydrates": "21,41 г"
    },
    {
        "name": "Фаст-фуд, английский кекс, с сыром и сосиской",
        "calories": "338 кКал",
        "priteins": "13,28 г",
        "fats": "20,67 г",
        "carbohydrates": "24,78 г"
    },
    {
        "name": "Фаст-фуд, английский кекс, с яйцом, сыром и канадским беконом",
        "calories": "228 кКал",
        "priteins": "13,64 г",
        "fats": "9,66 г",
        "carbohydrates": "21,27 г"
    },
    {
        "name": "Фаст-фуд, английский кекс, с яйцом, сыром и сосиской",
        "calories": "286 кКал",
        "priteins": "13,38 г",
        "fats": "18,1 г",
        "carbohydrates": "17,24 г"
    },
    {
        "name": "Фаст-фуд, бисквит с ветчиной",
        "calories": "342 кКал",
        "priteins": "11,85 г",
        "fats": "16,3 г",
        "carbohydrates": "38,05 г"
    },
    {
        "name": "Фаст-фуд, бисквит с сосиской",
        "calories": "371 кКал",
        "priteins": "9,67 г",
        "fats": "24,42 г",
        "carbohydrates": "29,59 г"
    },
    {
        "name": "Фаст-фуд, бисквит с яйцом и беконом",
        "calories": "305 кКал",
        "priteins": "11,33 г",
        "fats": "20,73 г",
        "carbohydrates": "18,56 г"
    },
    {
        "name": "Фаст-фуд, бисквит с яйцом и ветчиной",
        "calories": "233 кКал",
        "priteins": "10,64 г",
        "fats": "14,08 г",
        "carbohydrates": "15,97 г"
    },
    {
        "name": "Фаст-фуд, бисквит с яйцом и сосиской",
        "calories": "312 кКал",
        "priteins": "11,13 г",
        "fats": "20,77 г",
        "carbohydrates": "20,85 г"
    },
    {
        "name": "Фаст-фуд, бисквит с яйцом, сыром и сосиской",
        "calories": "301 кКал",
        "priteins": "12,01 г",
        "fats": "17,48 г",
        "carbohydrates": "24,24 г"
    },
    {
        "name": "Фаст-фуд, бублик с отбивной, яйцом и сыром, приправленный",
        "calories": "295 кКал",
        "priteins": "12,98 г",
        "fats": "16,97 г",
        "carbohydrates": "22,44 г"
    },
    {
        "name": "Фаст-фуд, бублик со стейком, яйцом и сыром, приправленный",
        "calories": "282 кКал",
        "priteins": "15,95 г",
        "fats": "14,07 г",
        "carbohydrates": "22,79 г"
    },
    {
        "name": "Фаст-фуд, буррито с бобами",
        "calories": "206 кКал",
        "priteins": "6,48 г",
        "fats": "6,22 г",
        "carbohydrates": "32,92 г"
    },
    {
        "name": "Фаст-фуд, буррито с бобами и мясом",
        "calories": "191 кКал",
        "priteins": "11,52 г",
        "fats": "7,47 г",
        "carbohydrates": "16,52 г"
    },
    {
        "name": "Фаст-фуд, буррито с бобами и сыром",
        "calories": "205 кКал",
        "priteins": "7,35 г",
        "fats": "6,05 г",
        "carbohydrates": "27,03 г"
    },
    {
        "name": "Фаст-фуд, буррито с бобами, сыром и говядиной",
        "calories": "180 кКал",
        "priteins": "7,03 г",
        "fats": "6,8 г",
        "carbohydrates": "19,67 г"
    },
    {
        "name": "Фаст-фуд, гамбургер, большой, с одной котлетой, приправленный",
        "calories": "256 кКал",
        "priteins": "15,68 г",
        "fats": "11,6 г",
        "carbohydrates": "21,04 г"
    },
    {
        "name": "Фаст-фуд, гамбургер, двойной, с большой котлетой, овощами и майонезом, приправленный",
        "calories": "252 кКал",
        "priteins": "13,94 г",
        "fats": "15,66 г",
        "carbohydrates": "12,34 г"
    },
    {
        "name": "Фаст-фуд, гамбургер, двойной, с одной стандартной котлетой, с приправами и фирменным соусом",
        "calories": "259 кКал",
        "priteins": "12,17 г",
        "fats": "13,3 г",
        "carbohydrates": "21,29 г"
    },
    {
        "name": "Фаст-фуд, гамбургер, с одной большой котлетой, овощами и майонезом, приправленный",
        "calories": "226 кКал",
        "priteins": "11,34 г",
        "fats": "12,37 г",
        "carbohydrates": "15,83 г"
    },
    {
        "name": "Фаст-фуд, гамбургер, с одной стандартной котлетой, неприправленный",
        "calories": "297 кКал",
        "priteins": "16,52 г",
        "fats": "12,01 г",
        "carbohydrates": "29,8 г"
    },
    {
        "name": "Фаст-фуд, гамбургер, с одной стандартной котлетой, приправленный",
        "calories": "263 кКал",
        "priteins": "13,3 г",
        "fats": "10,18 г",
        "carbohydrates": "27,77 г"
    },
    {
        "name": "Фаст-фуд, гренки по-французски",
        "calories": "340 кКал",
        "priteins": "6 г",
        "fats": "17,74 г",
        "carbohydrates": "39,81 г"
    },
    {
        "name": "Фаст-фуд, драники",
        "calories": "272 кКал",
        "priteins": "2,58 г",
        "fats": "17,04 г",
        "carbohydrates": "26,18 г"
    },
    {
        "name": "Фаст-фуд, картошка фри, жаренная в растительном масле",
        "calories": "312 кКал",
        "priteins": "3,43 г",
        "fats": "14,73 г",
        "carbohydrates": "37,64 г"
    },
    {
        "name": "Фаст-фуд, картошка-пюре",
        "calories": "89 кКал",
        "priteins": "1,65 г",
        "fats": "2,82 г",
        "carbohydrates": "13,35 г"
    },
    {
        "name": "Фаст-фуд, креветки, обжаренные в панировке",
        "calories": "308 кКал",
        "priteins": "7,84 г",
        "fats": "18,9 г",
        "carbohydrates": "27,29 г"
    },
    {
        "name": "Фаст-фуд, круассан с яйцом, сыром и беконом",
        "calories": "289 кКал",
        "priteins": "12,92 г",
        "fats": "16,4 г",
        "carbohydrates": "21,5 г"
    },
    {
        "name": "Фаст-фуд, круассан с яйцом, сыром и ветчиной",
        "calories": "261 кКал",
        "priteins": "12,45 г",
        "fats": "14,95 г",
        "carbohydrates": "18,08 г"
    },
    {
        "name": "Фаст-фуд, круассан с яйцом, сыром и сосиской",
        "calories": "308 кКал",
        "priteins": "12,09 г",
        "fats": "21,78 г",
        "carbohydrates": "14,1 г"
    },
    {
        "name": "Фаст-фуд, кукурузные оладьи",
        "calories": "296 кКал",
        "priteins": "6,16 г",
        "fats": "13,25 г",
        "carbohydrates": "37,31 г"
    },
    {
        "name": "Фаст-фуд, куриное филе",
        "calories": "271 кКал",
        "priteins": "19,22 г",
        "fats": "13,95 г",
        "carbohydrates": "16,05 г"
    },
    {
        "name": "Фаст-фуд, курица, обжаренная в панировке, без костей, неприправленная",
        "calories": "307 кКал",
        "priteins": "15,92 г",
        "fats": "20,36 г",
        "carbohydrates": "14,03 г"
    },
    {
        "name": "Фаст-фуд, луковые кольца, обжаренные в кляре",
        "calories": "411 кКал",
        "priteins": "3,86 г",
        "fats": "25,23 г",
        "carbohydrates": "40,88 г"
    },
    {
        "name": "Фаст-фуд, миниатюрные коричные рулеты",
        "calories": "403 кКал",
        "priteins": "7,02 г",
        "fats": "17,95 г",
        "carbohydrates": "51,18 г"
    },
    {
        "name": "Фаст-фуд, мягкое ванильное молочное мороженое в рожке",
        "calories": "163 кКал",
        "priteins": "4,24 г",
        "fats": "4,86 г",
        "carbohydrates": "26,26 г"
    },
    {
        "name": "Фаст-фуд, начо с сыром",
        "calories": "343 кКал",
        "priteins": "4,32 г",
        "fats": "21,5 г",
        "carbohydrates": "31,71 г"
    },
    {
        "name": "Фаст-фуд, начо с сыром, бобами, говяжьим фаршем и перцем",
        "calories": "219 кКал",
        "priteins": "6,21 г",
        "fats": "12,48 г",
        "carbohydrates": "17,69 г"
    },
    {
        "name": "Фаст-фуд, пицца с мясом и овощами, на стандартном корже, 14 дюймов",
        "calories": "244 кКал",
        "priteins": "11,02 г",
        "fats": "10,9 г",
        "carbohydrates": "23,18 г"
    },
    {
        "name": "Фаст-фуд, пицца с паперони, на стандартном корже, 14 дюймов",
        "calories": "282 кКал",
        "priteins": "11,74 г",
        "fats": "11,91 г",
        "carbohydrates": "29,68 г"
    },
    {
        "name": "Фаст-фуд, пицца с паперони, на толстом корже, 14 дюймов",
        "calories": "287 кКал",
        "priteins": "11,49 г",
        "fats": "12,58 г",
        "carbohydrates": "29,64 г"
    },
    {
        "name": "Фаст-фуд, пицца с сыром, на стандартном корже, 14 дюймов",
        "calories": "266 кКал",
        "priteins": "11,39 г",
        "fats": "9,69 г",
        "carbohydrates": "31,03 г"
    },
    {
        "name": "Фаст-фуд, пицца с сыром, на толстом корже, 14 дюймов",
        "calories": "271 кКал",
        "priteins": "10,81 г",
        "fats": "10,54 г",
        "carbohydrates": "30,97 г"
    },
    {
        "name": "Фаст-фуд, пицца с сыром, на тонком корже, 14 дюймов",
        "calories": "302 кКал",
        "priteins": "12,85 г",
        "fats": "13,95 г",
        "carbohydrates": "28,7 г"
    },
    {
        "name": "Фаст-фуд, пломбир с горячей помадкой",
        "calories": "180 кКал",
        "priteins": "3,57 г",
        "fats": "5,46 г",
        "carbohydrates": "30,17 г"
    },
    {
        "name": "Фаст-фуд, пломбир с карамелью",
        "calories": "196 кКал",
        "priteins": "4,71 г",
        "fats": "5,98 г",
        "carbohydrates": "31,81 г"
    },
    {
        "name": "Фаст-фуд, пломбир с клубникой",
        "calories": "175 кКал",
        "priteins": "4,09 г",
        "fats": "5,13 г",
        "carbohydrates": "29,18 г"
    },
    {
        "name": "Фаст-фуд, рыбный сэндвич с соусом тартар",
        "calories": "257 кКал",
        "priteins": "10,29 г",
        "fats": "12,45 г",
        "carbohydrates": "25,69 г"
    },
    {
        "name": "Фаст-фуд, рыбный сэндвич с соусом тартар и сыром",
        "calories": "279 кКал",
        "priteins": "11,26 г",
        "fats": "14,64 г",
        "carbohydrates": "25,59 г"
    },
    {
        "name": "Фаст-фуд, салат из капусты",
        "calories": "153 кКал",
        "priteins": "0,95 г",
        "fats": "9,91 г",
        "carbohydrates": "12,99 г"
    },
    {
        "name": "Фаст-фуд, сэндвич \"Субмарина\" с мясной нарезкой",
        "calories": "213 кКал",
        "priteins": "10,52 г",
        "fats": "10,04 г",
        "carbohydrates": "19,23 г"
    },
    {
        "name": "Фаст-фуд, сэндвич \"Субмарина\" с ростбифом",
        "calories": "190 кКал",
        "priteins": "13,26 г",
        "fats": "6 г",
        "carbohydrates": "20,51 г"
    },
    {
        "name": "Фаст-фуд, сэндвич \"Субмарина\" с салатом из тунца",
        "calories": "228 кКал",
        "priteins": "11,6 г",
        "fats": "10,93 г",
        "carbohydrates": "21,63 г"
    },
    {
        "name": "Фаст-фуд, сэндвич с куриным филе, неприправленный",
        "calories": "283 кКал",
        "priteins": "13,25 г",
        "fats": "16,18 г",
        "carbohydrates": "21,26 г"
    },
    {
        "name": "Фаст-фуд, сэндвич с поджаренным куриным филе, латуком, томатами и майонезом",
        "calories": "276 кКал",
        "priteins": "10,94 г",
        "fats": "13,59 г",
        "carbohydrates": "26 г"
    },
    {
        "name": "Фаст-фуд, сэндвич с ростбифом, неприправленный",
        "calories": "244 кКал",
        "priteins": "15,17 г",
        "fats": "10,3 г",
        "carbohydrates": "20,91 г"
    },
    {
        "name": "Фаст-фуд, тако",
        "calories": "226 кКал",
        "priteins": "8,86 г",
        "fats": "12,7 г",
        "carbohydrates": "15,95 г"
    },
    {
        "name": "Фаст-фуд, чизбургер, двойной, с большой котлетой, овощами и майонезом, приправленный",
        "calories": "253 кКал",
        "priteins": "15,5 г",
        "fats": "15,63 г",
        "carbohydrates": "11,32 г"
    },
    {
        "name": "Фаст-фуд, чизбургер, двойной, с большой котлетой, приправленный",
        "calories": "272 кКал",
        "priteins": "16,96 г",
        "fats": "16,22 г",
        "carbohydrates": "13,43 г"
    },
    {
        "name": "Фаст-фуд, чизбургер, двойной, со стандартной котлетой, приправленный",
        "calories": "282 кКал",
        "priteins": "16,24 г",
        "fats": "16,18 г",
        "carbohydrates": "17,07 г"
    },
    {
        "name": "Фаст-фуд, чизбургер, двойной, со стандартной котлетой, с приправами и фирменным соусом",
        "calories": "261 кКал",
        "priteins": "11,94 г",
        "fats": "14,1 г",
        "carbohydrates": "20,13 г"
    },
    {
        "name": "Фаст-фуд, чизбургер, с большой котлетой, неприправленный",
        "calories": "310 кКал",
        "priteins": "17,29 г",
        "fats": "15,97 г",
        "carbohydrates": "22,37 г"
    },
    {
        "name": "Фаст-фуд, чизбургер, с большой котлетой, овощами и майонезом, приправленный",
        "calories": "268 кКал",
        "priteins": "13,69 г",
        "fats": "15,8 г",
        "carbohydrates": "16,63 г"
    },
    {
        "name": "Фаст-фуд, чизбургер, с большой котлетой, приправленный",
        "calories": "269 кКал",
        "priteins": "15,21 г",
        "fats": "14,4 г",
        "carbohydrates": "18,52 г"
    },
    {
        "name": "Фаст-фуд, чизбургер, со стандартной котлетой и овощами, приправленный",
        "calories": "254 кКал",
        "priteins": "13,06 г",
        "fats": "11,5 г",
        "carbohydrates": "23,57 г"
    },
    {
        "name": "Фаст-фуд, чизбургер, со стандартной котлетой, неприправленный",
        "calories": "308 кКал",
        "priteins": "16,51 г",
        "fats": "14,72 г",
        "carbohydrates": "26,03 г"
    },
    {
        "name": "Фаст-фуд, чизбургер, со стандартной котлетой, приправленный",
        "calories": "270 кКал",
        "priteins": "13,49 г",
        "fats": "12,9 г",
        "carbohydrates": "23,56 г"
    },
    {
        "name": "Фаст-фуд, чизбургер, стандартный, с двумя котлетами и булочками, неприправленный",
        "calories": "305 кКал",
        "priteins": "15,13 г",
        "fats": "13,93 г",
        "carbohydrates": "29,89 г"
    },
    {
        "name": "Фаст-фуд, яичница-болтунья",
        "calories": "212 кКал",
        "priteins": "13,84 г",
        "fats": "16,18 г",
        "carbohydrates": "2,08 г"
    }
]